README.md
setup.py
mysmallutils.egg-info/PKG-INFO
mysmallutils.egg-info/SOURCES.txt
mysmallutils.egg-info/dependency_links.txt
mysmallutils.egg-info/top_level.txt
mysutils/__init__.py
mysutils/cli.py
mysutils/command.py
mysutils/config.py
mysutils/fastapi.py
mysutils/file.py
mysutils/hash.py
mysutils/logging.py
mysutils/method.py
mysutils/misc.py
mysutils/request.py
mysutils/service.py
mysutils/tar.py
mysutils/text.py
mysutils/tmp.py
mysutils/unittest.py
mysutils/web.py
mysutils/yaml.py
mysutils/collections/__init__.py
mysutils/collections/fifoqueuethread.py
mysutils/collections/lrudict.py
mysutils/collections/orderedset.py
mysutils/collections/utils.py
test/test_cli.py
test/test_collections.py
test/test_command.py
test/test_config.py
test/test_fastapi.py
test/test_fifoqueue.py
test/test_file.py
test/test_hash.py
test/test_logging.py
test/test_method.py
test/test_misc.py
test/test_orderedset.py
test/test_tar.py
test/test_temp.py
test/test_text.py
test/test_web.py