Metadata-Version: 2.1
Name: mysmallutils
Version: 2.1.3
Summary: Small Python utils to do life easier.
Home-page: https://github.com/jmgomezsoriano/mysmallutils
Author: José Manuel Gómez Soriano
Author-email: jmgomez.soriano@gmail.com
License: LGPL2
Classifier: Programming Language :: Python :: 3
Classifier: License :: OSI Approved :: MIT License
Classifier: Operating System :: OS Independent
Requires-Python: >=3.7,<4
